<?xml version="1.0" encoding="UTF-8"?>
<!--

    Copyright (c) 2008-2018, Massachusetts Institute of Technology (MIT)
    All rights reserved.

    Redistribution and use in source and binary forms, with or without
    modification, are permitted provided that the following conditions are met:

    1. Redistributions of source code must retain the above copyright notice, this
    list of conditions and the following disclaimer.

    2. Redistributions in binary form must reproduce the above copyright notice,
    this list of conditions and the following disclaimer in the documentation
    and/or other materials provided with the distribution.

    3. Neither the name of the copyright holder nor the names of its contributors
    may be used to endorse or promote products derived from this software without
    specific prior written permission.

    THIS SOFTWARE IS PROVIDED BY THE COPYRIGHT HOLDERS AND CONTRIBUTORS "AS IS"
    AND ANY EXPRESS OR IMPLIED WARRANTIES, INCLUDING, BUT NOT LIMITED TO, THE
    IMPLIED WARRANTIES OF MERCHANTABILITY AND FITNESS FOR A PARTICULAR PURPOSE ARE
    DISCLAIMED. IN NO EVENT SHALL THE COPYRIGHT HOLDER OR CONTRIBUTORS BE LIABLE
    FOR ANY DIRECT, INDIRECT, INCIDENTAL, SPECIAL, EXEMPLARY, OR CONSEQUENTIAL
    DAMAGES (INCLUDING, BUT NOT LIMITED TO, PROCUREMENT OF SUBSTITUTE GOODS OR
    SERVICES; LOSS OF USE, DATA, OR PROFITS; OR BUSINESS INTERRUPTION) HOWEVER
    CAUSED AND ON ANY THEORY OF LIABILITY, WHETHER IN CONTRACT, STRICT LIABILITY,
    OR TORT (INCLUDING NEGLIGENCE OR OTHERWISE) ARISING IN ANY WAY OUT OF THE USE
    OF THIS SOFTWARE, EVEN IF ADVISED OF THE POSSIBILITY OF SUCH DAMAGE.

-->
<beans xmlns="http://www.springframework.org/schema/beans"
	xmlns:xsi="http://www.w3.org/2001/XMLSchema-instance" xmlns:jaxrs="http://cxf.apache.org/jaxrs"
	xmlns:cxf="http://cxf.apache.org/core"
	xmlns:jee="http://www.springframework.org/schema/jee"
    xmlns:context="http://www.springframework.org/schema/context"
	xsi:schemaLocation="http://cxf.apache.org/core http://cxf.apache.org/schemas/core.xsd
		http://www.springframework.org/schema/beans http://www.springframework.org/schema/beans/spring-beans.xsd
		http://cxf.apache.org/jaxrs http://cxf.apache.org/schemas/jaxrs.xsd
		http://www.springframework.org/schema/jee http://www.springframework.org/schema/jee/spring-jee.xsd
		http://www.springframework.org/schema/context http://www.springframework.org/schema/context/spring-context-4.0.xsd">

	<jee:jndi-lookup id="dataSource" jndi-name="jboss/sadisplayDatasource" resource-ref="true" />

	<bean id="loggingFeature" class="org.apache.cxf.feature.LoggingFeature" />
    <context:annotation-config/>

    <bean id="configuration1" class="edu.mit.ll.em.api.configuration.SpringConfiguration"/>
    <bean id="validationProvider" class="org.apache.cxf.validation.BeanValidationProvider"/>
    <bean id="validationInInterceptor" class="org.apache.cxf.jaxrs.validation.JAXRSBeanValidationInInterceptor"/>

	<jaxrs:server id="apiv1Resource" address="/">
		<jaxrs:properties>
			<entry key="attachment-directory" value="temp"/>
			<!-- 50MB-->
			<entry key="attachment-memory-threshold" value="51200000"/>

			<entry key="attachment-max-size" value="51200000"/>
		</jaxrs:properties>

        <jaxrs:inInterceptors>
            <ref bean="validationInInterceptor"/>
        </jaxrs:inInterceptors>

		<jaxrs:serviceBeans>
			<bean class="edu.mit.ll.em.api.rs.impl.ChatMsgServiceImpl" />
			<bean class="edu.mit.ll.em.api.rs.impl.AnnouncementServiceImpl" />
			<bean class="edu.mit.ll.em.api.rs.impl.CollabServiceImpl" />
			<bean class="edu.mit.ll.em.api.rs.impl.DatalayerExportImpl" />
			<bean class="edu.mit.ll.em.api.rs.impl.DatalayerServiceImpl" >
				<constructor-arg ref="emApiConfiguration" />
                <constructor-arg ref="datalayerDao" />
                <constructor-arg ref="folderDao" />
                <constructor-arg ref="documentDao" />
                <constructor-arg ref="userDao" />
                <constructor-arg ref="userOrgDao" />
                <constructor-arg ref="userSessionDao" />
                <constructor-arg ref="rabbitProducer" />
                <constructor-arg ref="jerseyClient" />
			</bean>
			<!-- <bean class="edu.mit.ll.em.api.rs.impl.DatalayerBreadCrumbsImpl" /> -->
			<bean class="edu.mit.ll.em.api.rs.impl.FeatureServiceImpl" />
			<bean class="edu.mit.ll.em.api.rs.impl.FolderServiceImpl" />
			<bean class="edu.mit.ll.em.api.rs.impl.IncidentServiceImpl" />
			<bean class="edu.mit.ll.em.api.rs.impl.LoginServiceImpl" >
                <constructor-arg ref="userDao"/>
                <constructor-arg ref="userSessionDao"/>
                <constructor-arg ref="userOrgDao"/>
                <constructor-arg ref="orgDao"/>
                <constructor-arg ref="workspaceDao"/>
                <constructor-arg ref="rabbitProducer"/>
            </bean>
			<bean class="edu.mit.ll.em.api.rs.impl.MDTrackServiceImpl" />
			<!-- <bean class="edu.mit.ll.em.api.rs.impl.MsgBusServiceImpl" /> -->
			<bean class="edu.mit.ll.em.api.rs.impl.OrganizationServiceImpl" />
			<bean class="edu.mit.ll.em.api.rs.impl.ReportServiceImpl" />
			<bean class="edu.mit.ll.em.api.rs.impl.SSOManagementServiceImpl" />
			<!-- <bean class="edu.mit.ll.em.api.rs.impl.TaskingAssignmentServiceImpl" /> -->
			<bean class="edu.mit.ll.em.api.rs.impl.UserServiceImpl">
                <constructor-arg ref="workspaceDao" />
                <constructor-arg ref="registrationService"/>
                <constructor-arg ref="validator"/>
            </bean>
			<bean class="edu.mit.ll.em.api.rs.impl.WorkspaceServiceImpl" />
		</jaxrs:serviceBeans>

		<jaxrs:features>
			<ref bean="loggingFeature" />
		</jaxrs:features>

		<jaxrs:providers>
			<bean class="org.codehaus.jackson.jaxrs.JacksonJsonProvider" />
            <bean class="edu.mit.ll.em.api.rs.exceptionMapper.ValidationExceptionMapper"/>
		</jaxrs:providers>
	</jaxrs:server>
</beans>
